{"gallery":
    {
    "1":{
        "image":"1.png",
        "caption":"Game Dev Workshop 1 "
    },
    "2":{
        "image":"2.png",
        "caption":"Game Dev Workshop 2 "
    },   
    "3":{
        "image":"3.png",
        "caption":"Game Dev Workshop 3"
    },
    "4":{
        "image":"3.png",
        "caption":"Game Dev Workshop 4"
    },
    "5":{
        "image":"1.png",
        "caption":"Game Dev Workshop 5"
    },   
    "6":{
        "image":"2.png",
        "caption":"Game Dev Workshop 6"
    }
}
}